pibooth_fire_remote.py
pibooth_fire_remote-0.2.2.dist-info/LICENSE
pibooth_fire_remote-0.2.2.dist-info/METADATA
pibooth_fire_remote-0.2.2.dist-info/WHEEL
pibooth_fire_remote-0.2.2.dist-info/entry_points.txt
pibooth_fire_remote-0.2.2.dist-info/top_level.txt
pibooth_fire_remote-0.2.2.dist-info/RECORD
